adminactions/__init__.py
adminactions/actions.py
adminactions/api.py
adminactions/apps.py
adminactions/bulk_update.py
adminactions/byrows_update.py
adminactions/checks.py
adminactions/compat.py
adminactions/config.py
adminactions/consts.py
adminactions/duplicates.py
adminactions/exceptions.py
adminactions/export.py
adminactions/forms.py
adminactions/graph.py
adminactions/helpers.py
adminactions/mass_update.py
adminactions/merge.py
adminactions/models.py
adminactions/perms.py
adminactions/py.typed
adminactions/signals.py
adminactions/tasks.py
adminactions/urls.py
adminactions/utils.py
adminactions/version.py
adminactions/views.py
adminactions/locale/en/LC_MESSAGES/django.mo
adminactions/locale/en/LC_MESSAGES/django.po
adminactions/locale/es/LC_MESSAGES/django.mo
adminactions/locale/es/LC_MESSAGES/django.po
adminactions/locale/fr/LC_MESSAGES/django.mo
adminactions/locale/fr/LC_MESSAGES/django.po
adminactions/locale/it/LC_MESSAGES/django.mo
adminactions/locale/it/LC_MESSAGES/django.po
adminactions/locale/pl/LC_MESSAGES/django.mo
adminactions/locale/pl/LC_MESSAGES/django.po
adminactions/locale/pt_BR/LC_MESSAGES/django.mo
adminactions/locale/pt_BR/LC_MESSAGES/django.po
adminactions/management/__init__.py
adminactions/management/commands/__init__.py
adminactions/management/commands/create_extra_permissions.py
adminactions/static/adminactions/css/adminactions.css
adminactions/static/adminactions/css/adminactions.css.map
adminactions/static/adminactions/css/adminactions.scss
adminactions/static/adminactions/css/bulkupdate.css
adminactions/static/adminactions/css/bulkupdate.css.map
adminactions/static/adminactions/css/bulkupdate.scss
adminactions/static/adminactions/css/massupdate.css
adminactions/static/adminactions/css/massupdate.css.map
adminactions/static/adminactions/css/massupdate.scss
adminactions/static/adminactions/js/bulkupdate.js
adminactions/static/adminactions/js/bulkupdate.min.js
adminactions/static/adminactions/js/export.js
django_adminactions-2.4.dist-info/METADATA
django_adminactions-2.4.dist-info/WHEEL
django_adminactions-2.4.dist-info/licenses/AUTHORS.md
django_adminactions-2.4.dist-info/licenses/LICENSE
django_adminactions-2.4.dist-info/RECORD
