Metadata-Version: 2.4
Name: django-adminactions
Version: 2.4
Summary: Collections of useful actions to use with django.contrib.admin.ModelAdmin
Project-URL: downloads, https://github.com/saxix/django-adminactions
Project-URL: homepage, https://github.com/saxix/django-adminactions
Author-email: sax <s.apostolico@gmail.com>
Maintainer-email: Stefano Apostolico <s.apostolico@gmail.com>
License: MIT License
License-File: AUTHORS.md
License-File: LICENSE
Classifier: Environment :: Web Environment
Classifier: Framework :: Django
Classifier: Framework :: Django :: 3.2
Classifier: Framework :: Django :: 4.2
Classifier: Framework :: Django :: 5.1
Classifier: Intended Audience :: Developers
Classifier: Operating System :: OS Independent
Classifier: Programming Language :: Python :: 3 :: Only
Classifier: Programming Language :: Python :: 3.10
Classifier: Programming Language :: Python :: 3.11
Classifier: Programming Language :: Python :: 3.12
Classifier: Programming Language :: Python :: 3.13
Requires-Python: >=3.10
Requires-Dist: django-stubs-ext>=5.1.3
Requires-Dist: pytz
Requires-Dist: xlrd>=0.9.2
Requires-Dist: xlwt
Provides-Extra: dev
